ezpyinline.py
setup.py
ezpyinline.egg-info/PKG-INFO
ezpyinline.egg-info/SOURCES.txt
ezpyinline.egg-info/dependency_links.txt
ezpyinline.egg-info/top_level.txt
