Metadata-Version: 1.0
Name: ezpyinline
Version: 0.1
Summary: Easy embedded Inline C for Python
Home-page: http://ezpyinline.sf.net
Author: __tim__
Author-email: timchen119@gmail.com
License: Artistic
Platform: any
Classifier: Development Status :: 2 - Pre-Alpha
Classifier: Intended Audience :: Developers
Classifier: License :: OSI Approved :: Artistic License
Classifier: Programming Language :: Python
Classifier: Operating System :: OS Independent
Classifier: Natural Language :: English
Classifier: Topic :: Software Development :: Build Tools
